{"data":[{"type":"gif","id":"LS8UjvdGL7e5OtQoKv","slug":"mlb-hands-waving-LS8UjvdGL7e5OtQoKv","url":"https:\/\/giphy.com\/gifs\/mlb-hands-waving-LS8UjvdGL7e5OtQoKv","bitly_gif_url":"https:\/\/gph.is\/g\/aNWWlLo","bitly_url":"https:\/\/gph.is\/g\/aNWWlLo","embed_url":"https:\/\/giphy.com\/embed\/LS8UjvdGL7e5OtQoKv","username":"mlb","source":"https:\/\/mlb.com","rating":"g","content_url":"","source_tld":"mlb.com","source_post_url":"https:\/\/mlb.com","is_sticker":0,"import_datetime":"2019-08-17 07:00:28","trending_datetime":"2019-08-20 15:14:06","user":{"avatar_url":"https:\/\/media1.giphy.com\/channel_assets\/mlb\/jL0oCFBZsURo.png","banner_url":"https:\/\/media1.giphy.com\/channel_assets\/mlb\/8Y39J0Q4HSYL.gif","banner_image":"https:\/\/media1.giphy.com\/channel_assets\/mlb\/8Y39J0Q4HSYL.gif","profile_url":"https:\/\/giphy.com\/mlb\/","username":"mlb","display_name":"MLB","is_verified":true},"images":{"fixed_height_still":{"url":"https:\/\/media1.giphy.com\/media\/LS8UjvdGL7e5OtQoKv\/200_s.gif?cid=f8e0ca6fa1cd021474189f345a08e0ded78f34ab4ca59f6d&rid=200_s.gif","width":"356","height":"200","size":"28707"},"original_still":{"url":"https:\/\/media1.giphy.com\/media\/LS8UjvdGL7e5OtQoKv\/giphy_s.gif?cid=f8e0ca6fa1cd021474189f345a08e0ded78f34ab4ca59f6d&rid=giphy_s.gif","width":"512","height":"288","size":"88701"},"fixed_width":{"url":"https:\/\/media1.giphy.com\/media\/LS8UjvdGL7e5OtQoKv\/200w.gif?cid=f8e0ca6fa1cd021474189f345a08e0ded78f34ab4ca59f6d&rid=200w.gif","width":"200","height":"113","size":"337898","mp4":"https:\/\/media1.giphy.com\/media\/LS8UjvdGL7e5OtQoKv\/200w.mp4?cid=f8e0ca6fa1cd021474189f345a08e0ded78f34ab4ca59f6d&rid=200w.mp4","mp4_size":"89997","webp":"https:\/\/media1.giphy.com\/media\/LS8UjvdGL7e5OtQoKv\/200w.webp?cid=f8e0ca6fa1cd021474189f345a08e0ded78f34ab4ca59f6d&rid=200w.webp","webp_size":"173306"},"fixed_height_small_still":{"url":"https:\/\/media1.giphy.com\/media\/LS8UjvdGL7e5OtQoKv\/100_s.gif?cid=f8e0ca6fa1cd021474189f345a08e0ded78f34ab4ca59f6d&rid=100_s.gif","width":"178","height":"100","size":"11480"},"fixed_height_downsampled":{"url":"https:\/\/media1.giphy.com\/media\/LS8UjvdGL7e5OtQoKv\/200_d.gif?cid=f8e0ca6fa1cd021474189f345a08e0ded78f34ab4ca59f6d&rid=200_d.gif","width":"356","height":"200","size":"181105","webp":"https:\/\/media1.giphy.com\/media\/LS8UjvdGL7e5OtQoKv\/200_d.webp?cid=f8e0ca6fa1cd021474189f345a08e0ded78f34ab4ca59f6d&rid=200_d.webp","webp_size":"109836"},"preview":{"width":"259","height":"146","mp4":"https:\/\/media1.giphy.com\/media\/LS8UjvdGL7e5OtQoKv\/giphy-preview.mp4?cid=f8e0ca6fa1cd021474189f345a08e0ded78f34ab4ca59f6d&rid=giphy-preview.mp4","mp4_size":"41075"},"fixed_height_small":{"url":"https:\/\/media1.giphy.com\/media\/LS8UjvdGL7e5OtQoKv\/100.gif?cid=f8e0ca6fa1cd021474189f345a08e0ded78f34ab4ca59f6d&rid=100.gif","width":"178","height":"100","size":"272616","mp4":"https:\/\/media1.giphy.com\/media\/LS8UjvdGL7e5OtQoKv\/100.mp4?cid=f8e0ca6fa1cd021474189f345a08e0ded78f34ab4ca59f6d&rid=100.mp4","mp4_size":"80374","webp":"https:\/\/media1.giphy.com\/media\/LS8UjvdGL7e5OtQoKv\/100.webp?cid=f8e0ca6fa1cd021474189f345a08e0ded78f34ab4ca59f6d&rid=100.webp","webp_size":"150978"},"downsized_still":{"url":"https:\/\/media1.giphy.com\/media\/LS8UjvdGL7e5OtQoKv\/giphy-downsized_s.gif?cid=f8e0ca6fa1cd021474189f345a08e0ded78f34ab4ca59f6d&rid=giphy-downsized_s.gif","width":"512","height":"288","size":"45071"},"downsized":{"url":"https:\/\/media1.giphy.com\/media\/LS8UjvdGL7e5OtQoKv\/giphy-downsized.gif?cid=f8e0ca6fa1cd021474189f345a08e0ded78f34ab4ca59f6d&rid=giphy-downsized.gif","width":"512","height":"288","size":"1284812"},"downsized_large":{"url":"https:\/\/media1.giphy.com\/media\/LS8UjvdGL7e5OtQoKv\/giphy.gif?cid=f8e0ca6fa1cd021474189f345a08e0ded78f34ab4ca59f6d&rid=giphy.gif","width":"512","height":"288","size":"2103948"},"fixed_width_small_still":{"url":"https:\/\/media1.giphy.com\/media\/LS8UjvdGL7e5OtQoKv\/100w_s.gif?cid=f8e0ca6fa1cd021474189f345a08e0ded78f34ab4ca59f6d&rid=100w_s.gif","width":"100","height":"57","size":"4350"},"preview_webp":{"url":"https:\/\/media1.giphy.com\/media\/LS8UjvdGL7e5OtQoKv\/giphy-preview.webp?cid=f8e0ca6fa1cd021474189f345a08e0ded78f34ab4ca59f6d&rid=giphy-preview.webp","width":"174","height":"98","size":"46734"},"fixed_width_still":{"url":"https:\/\/media1.giphy.com\/media\/LS8UjvdGL7e5OtQoKv\/200w_s.gif?cid=f8e0ca6fa1cd021474189f345a08e0ded78f34ab4ca59f6d&rid=200w_s.gif","width":"200","height":"113","size":"15242"},"fixed_width_small":{"url":"https:\/\/media1.giphy.com\/media\/LS8UjvdGL7e5OtQoKv\/100w.gif?cid=f8e0ca6fa1cd021474189f345a08e0ded78f34ab4ca59f6d&rid=100w.gif","width":"100","height":"57","size":"110840","mp4":"https:\/\/media1.giphy.com\/media\/LS8UjvdGL7e5OtQoKv\/100w.mp4?cid=f8e0ca6fa1cd021474189f345a08e0ded78f34ab4ca59f6d&rid=100w.mp4","mp4_size":"35186","webp":"https:\/\/media1.giphy.com\/media\/LS8UjvdGL7e5OtQoKv\/100w.webp?cid=f8e0ca6fa1cd021474189f345a08e0ded78f34ab4ca59f6d&rid=100w.webp","webp_size":"66400"},"downsized_small":{"width":"355","height":"200","mp4":"https:\/\/media1.giphy.com\/media\/LS8UjvdGL7e5OtQoKv\/giphy-downsized-small.mp4?cid=f8e0ca6fa1cd021474189f345a08e0ded78f34ab4ca59f6d&rid=giphy-downsized-small.mp4","mp4_size":"115773"},"fixed_width_downsampled":{"url":"https:\/\/media1.giphy.com\/media\/LS8UjvdGL7e5OtQoKv\/200w_d.gif?cid=f8e0ca6fa1cd021474189f345a08e0ded78f34ab4ca59f6d&rid=200w_d.gif","width":"200","height":"113","size":"66679","webp":"https:\/\/media1.giphy.com\/media\/LS8UjvdGL7e5OtQoKv\/200w_d.webp?cid=f8e0ca6fa1cd021474189f345a08e0ded78f34ab4ca59f6d&rid=200w_d.webp","webp_size":"42198"},"downsized_medium":{"url":"https:\/\/media1.giphy.com\/media\/LS8UjvdGL7e5OtQoKv\/giphy.gif?cid=f8e0ca6fa1cd021474189f345a08e0ded78f34ab4ca59f6d&rid=giphy.gif","width":"512","height":"288","size":"2103948"},"original":{"url":"https:\/\/media1.giphy.com\/media\/LS8UjvdGL7e5OtQoKv\/giphy.gif?cid=f8e0ca6fa1cd021474189f345a08e0ded78f34ab4ca59f6d&rid=giphy.gif","width":"512","height":"288","size":"2103948","frames":"31","mp4":"https:\/\/media1.giphy.com\/media\/LS8UjvdGL7e5OtQoKv\/giphy.mp4?cid=f8e0ca6fa1cd021474189f345a08e0ded78f34ab4ca59f6d&rid=giphy.mp4","mp4_size":"346896","webp":"https:\/\/media1.giphy.com\/media\/LS8UjvdGL7e5OtQoKv\/giphy.webp?cid=f8e0ca6fa1cd021474189f345a08e0ded78f34ab4ca59f6d&rid=giphy.webp","webp_size":"633578","hash":"67f893dfeca9c455e84ec723e7bd1fb7"},"fixed_height":{"url":"https:\/\/media1.giphy.com\/media\/LS8UjvdGL7e5OtQoKv\/200.gif?cid=f8e0ca6fa1cd021474189f345a08e0ded78f34ab4ca59f6d&rid=200.gif","width":"356","height":"200","size":"871333","mp4":"https:\/\/media1.giphy.com\/media\/LS8UjvdGL7e5OtQoKv\/200.mp4?cid=f8e0ca6fa1cd021474189f345a08e0ded78f34ab4ca59f6d&rid=200.mp4","mp4_size":"212291","webp":"https:\/\/media1.giphy.com\/media\/LS8UjvdGL7e5OtQoKv\/200.webp?cid=f8e0ca6fa1cd021474189f345a08e0ded78f34ab4ca59f6d&rid=200.webp","webp_size":"388968"},"looping":{"mp4":"https:\/\/media1.giphy.com\/media\/LS8UjvdGL7e5OtQoKv\/giphy-loop.mp4?cid=f8e0ca6fa1cd021474189f345a08e0ded78f34ab4ca59f6d&rid=giphy-loop.mp4","mp4_size":"2103087"},"original_mp4":{"width":"480","height":"270","mp4":"https:\/\/media1.giphy.com\/media\/LS8UjvdGL7e5OtQoKv\/giphy.mp4?cid=f8e0ca6fa1cd021474189f345a08e0ded78f34ab4ca59f6d&rid=giphy.mp4","mp4_size":"346896"},"preview_gif":{"url":"https:\/\/media1.giphy.com\/media\/LS8UjvdGL7e5OtQoKv\/giphy-preview.gif?cid=f8e0ca6fa1cd021474189f345a08e0ded78f34ab4ca59f6d&rid=giphy-preview.gif","width":"92","height":"52","size":"49727"},"480w_still":{"url":"https:\/\/media4.giphy.com\/media\/LS8UjvdGL7e5OtQoKv\/480w_s.jpg?cid=f8e0ca6fa1cd021474189f345a08e0ded78f34ab4ca59f6d&rid=480w_s.jpg","width":"480","height":"270"}},"title":"Waving Major League Baseball GIF by MLB","analytics":{"onload":{"url":"https:\/\/giphy-analytics.giphy.com\/simple_analytics?response_id=a1cd021474189f345a08e0ded78f34ab4ca59f6d&event_type=GIF_TRENDING&gif_id=LS8UjvdGL7e5OtQoKv&action_type=SEEN"},"onclick":{"url":"https:\/\/giphy-analytics.giphy.com\/simple_analytics?response_id=a1cd021474189f345a08e0ded78f34ab4ca59f6d&event_type=GIF_TRENDING&gif_id=LS8UjvdGL7e5OtQoKv&action_type=CLICK"},"onsent":{"url":"https:\/\/giphy-analytics.giphy.com\/simple_analytics?response_id=a1cd021474189f345a08e0ded78f34ab4ca59f6d&event_type=GIF_TRENDING&gif_id=LS8UjvdGL7e5OtQoKv&action_type=SENT"}}},{"type":"gif","id":"TgV0HNvu2jHnJ0gENC","slug":"bachelorinparadise-season-6-bachelor-in-paradise-yas-queen-TgV0HNvu2jHnJ0gENC","url":"https:\/\/giphy.com\/gifs\/bachelorinparadise-season-6-bachelor-in-paradise-yas-queen-TgV0HNvu2jHnJ0gENC","bitly_gif_url":"https:\/\/gph.is\/g\/E06rMMr","bitly_url":"https:\/\/gph.is\/g\/E06rMMr","embed_url":"https:\/\/giphy.com\/embed\/TgV0HNvu2jHnJ0gENC","username":"bachelorinparadise","source":"","rating":"g","content_url":"","source_tld":"","source_post_url":"","is_sticker":0,"import_datetime":"2019-08-19 19:50:29","trending_datetime":"2019-08-20 14:36:28","user":{"avatar_url":"https:\/\/media1.giphy.com\/avatars\/bachelorinparadise\/ArIVl2fyVLDM.jpg","banner_url":"https:\/\/media1.giphy.com\/headers\/bachelorinparadise\/tww1zKFKngcP.jpg","banner_image":"https:\/\/media1.giphy.com\/headers\/bachelorinparadise\/tww1zKFKngcP.jpg","profile_url":"https:\/\/giphy.com\/bachelorinparadise\/","username":"bachelorinparadise","display_name":"Bachelor in Paradise","is_verified":true},"images":{"fixed_height_still":{"url":"https:\/\/media1.giphy.com\/media\/TgV0HNvu2jHnJ0gENC\/200_s.gif?cid=f8e0ca6fa1cd021474189f345a08e0ded78f34ab4ca59f6d&rid=200_s.gif","width":"356","height":"200","size":"23239"},"original_still":{"url":"https:\/\/media1.giphy.com\/media\/TgV0HNvu2jHnJ0gENC\/giphy_s.gif?cid=f8e0ca6fa1cd021474189f345a08e0ded78f34ab4ca59f6d&rid=giphy_s.gif","width":"480","height":"270","size":"54672"},"fixed_width":{"url":"https:\/\/media1.giphy.com\/media\/TgV0HNvu2jHnJ0gENC\/200w.gif?cid=f8e0ca6fa1cd021474189f345a08e0ded78f34ab4ca59f6d&rid=200w.gif","width":"200","height":"113","size":"399149","mp4":"https:\/\/media1.giphy.com\/media\/TgV0HNvu2jHnJ0gENC\/200w.mp4?cid=f8e0ca6fa1cd021474189f345a08e0ded78f34ab4ca59f6d&rid=200w.mp4","mp4_size":"60935","webp":"https:\/\/media1.giphy.com\/media\/TgV0HNvu2jHnJ0gENC\/200w.webp?cid=f8e0ca6fa1cd021474189f345a08e0ded78f34ab4ca59f6d&rid=200w.webp","webp_size":"147552"},"fixed_height_small_still":{"url":"https:\/\/media1.giphy.com\/media\/TgV0HNvu2jHnJ0gENC\/100_s.gif?cid=f8e0ca6fa1cd021474189f345a08e0ded78f34ab4ca59f6d&rid=100_s.gif","width":"178","height":"100","size":"9077"},"fixed_height_downsampled":{"url":"https:\/\/media1.giphy.com\/media\/TgV0HNvu2jHnJ0gENC\/200_d.gif?cid=f8e0ca6fa1cd021474189f345a08e0ded78f34ab4ca59f6d&rid=200_d.gif","width":"356","height":"200","size":"145551","webp":"https:\/\/media1.giphy.com\/media\/TgV0HNvu2jHnJ0gENC\/200_d.webp?cid=f8e0ca6fa1cd021474189f345a08e0ded78f34ab4ca59f6d&rid=200_d.webp","webp_size":"85338"},"preview":{"width":"337","height":"190","mp4":"https:\/\/media1.giphy.com\/media\/TgV0HNvu2jHnJ0gENC\/giphy-preview.mp4?cid=f8e0ca6fa1cd021474189f345a08e0ded78f34ab4ca59f6d&rid=giphy-preview.mp4","mp4_size":"37185"},"fixed_height_small":{"url":"https:\/\/media1.giphy.com\/media\/TgV0HNvu2jHnJ0gENC\/100.gif?cid=f8e0ca6fa1cd021474189f345a08e0ded78f34ab4ca59f6d&rid=100.gif","width":"178","height":"100","size":"301782","mp4":"https:\/\/media1.giphy.com\/media\/TgV0HNvu2jHnJ0gENC\/100.mp4?cid=f8e0ca6fa1cd021474189f345a08e0ded78f34ab4ca59f6d&rid=100.mp4","mp4_size":"55434","webp":"https:\/\/media1.giphy.com\/media\/TgV0HNvu2jHnJ0gENC\/100.webp?cid=f8e0ca6fa1cd021474189f345a08e0ded78f34ab4ca59f6d&rid=100.webp","webp_size":"131772"},"downsized_still":{"url":"https:\/\/media1.giphy.com\/media\/TgV0HNvu2jHnJ0gENC\/giphy-downsized_s.gif?cid=f8e0ca6fa1cd021474189f345a08e0ded78f34ab4ca59f6d&rid=giphy-downsized_s.gif","width":"480","height":"270","size":"35707"},"downsized":{"url":"https:\/\/media1.giphy.com\/media\/TgV0HNvu2jHnJ0gENC\/giphy-downsized.gif?cid=f8e0ca6fa1cd021474189f345a08e0ded78f34ab4ca59f6d&rid=giphy-downsized.gif","width":"480","height":"270","size":"1232066"},"downsized_large":{"url":"https:\/\/media1.giphy.com\/media\/TgV0HNvu2jHnJ0gENC\/giphy.gif?cid=f8e0ca6fa1cd021474189f345a08e0ded78f34ab4ca59f6d&rid=giphy.gif","width":"480","height":"270","size":"2261234"},"fixed_width_small_still":{"url":"https:\/\/media1.giphy.com\/media\/TgV0HNvu2jHnJ0gENC\/100w_s.gif?cid=f8e0ca6fa1cd021474189f345a08e0ded78f34ab4ca59f6d&rid=100w_s.gif","width":"100","height":"57","size":"3841"},"preview_webp":{"url":"https:\/\/media1.giphy.com\/media\/TgV0HNvu2jHnJ0gENC\/giphy-preview.webp?cid=f8e0ca6fa1cd021474189f345a08e0ded78f34ab4ca59f6d&rid=giphy-preview.webp","width":"210","height":"118","size":"44670"},"fixed_width_still":{"url":"https:\/\/media1.giphy.com\/media\/TgV0HNvu2jHnJ0gENC\/200w_s.gif?cid=f8e0ca6fa1cd021474189f345a08e0ded78f34ab4ca59f6d&rid=200w_s.gif","width":"200","height":"113","size":"11933"},"fixed_width_small":{"url":"https:\/\/media1.giphy.com\/media\/TgV0HNvu2jHnJ0gENC\/100w.gif?cid=f8e0ca6fa1cd021474189f345a08e0ded78f34ab4ca59f6d&rid=100w.gif","width":"100","height":"57","size":"121563","mp4":"https:\/\/media1.giphy.com\/media\/TgV0HNvu2jHnJ0gENC\/100w.mp4?cid=f8e0ca6fa1cd021474189f345a08e0ded78f34ab4ca59f6d&rid=100w.mp4","mp4_size":"24189","webp":"https:\/\/media1.giphy.com\/media\/TgV0HNvu2jHnJ0gENC\/100w.webp?cid=f8e0ca6fa1cd021474189f345a08e0ded78f34ab4ca59f6d&rid=100w.webp","webp_size":"63000"},"downsized_small":{"width":"416","height":"234","mp4":"https:\/\/media1.giphy.com\/media\/TgV0HNvu2jHnJ0gENC\/giphy-downsized-small.mp4?cid=f8e0ca6fa1cd021474189f345a08e0ded78f34ab4ca59f6d&rid=giphy-downsized-small.mp4","mp4_size":"104135"},"fixed_width_downsampled":{"url":"https:\/\/media1.giphy.com\/media\/TgV0HNvu2jHnJ0gENC\/200w_d.gif?cid=f8e0ca6fa1cd021474189f345a08e0ded78f34ab4ca59f6d&rid=200w_d.gif","width":"200","height":"113","size":"60836","webp":"https:\/\/media1.giphy.com\/media\/TgV0HNvu2jHnJ0gENC\/200w_d.webp?cid=f8e0ca6fa1cd021474189f345a08e0ded78f34ab4ca59f6d&rid=200w_d.webp","webp_size":"35336"},"downsized_medium":{"url":"https:\/\/media1.giphy.com\/media\/TgV0HNvu2jHnJ0gENC\/giphy.gif?cid=f8e0ca6fa1cd021474189f345a08e0ded78f34ab4ca59f6d&rid=giphy.gif","width":"480","height":"270","size":"2261234"},"original":{"url":"https:\/\/media1.giphy.com\/media\/TgV0HNvu2jHnJ0gENC\/giphy.gif?cid=f8e0ca6fa1cd021474189f345a08e0ded78f34ab4ca59f6d&rid=giphy.gif","width":"480","height":"270","size":"2261234","frames":"42","mp4":"https:\/\/media1.giphy.com\/media\/TgV0HNvu2jHnJ0gENC\/giphy.mp4?cid=f8e0ca6fa1cd021474189f345a08e0ded78f34ab4ca59f6d&rid=giphy.mp4","mp4_size":"264489","webp":"https:\/\/media1.giphy.com\/media\/TgV0HNvu2jHnJ0gENC\/giphy.webp?cid=f8e0ca6fa1cd021474189f345a08e0ded78f34ab4ca59f6d&rid=giphy.webp","webp_size":"420802","hash":"e18b83db14f6345eff3cd2b80e463281"},"fixed_height":{"url":"https:\/\/media1.giphy.com\/media\/TgV0HNvu2jHnJ0gENC\/200.gif?cid=f8e0ca6fa1cd021474189f345a08e0ded78f34ab4ca59f6d&rid=200.gif","width":"356","height":"200","size":"909902","mp4":"https:\/\/media1.giphy.com\/media\/TgV0HNvu2jHnJ0gENC\/200.mp4?cid=f8e0ca6fa1cd021474189f345a08e0ded78f34ab4ca59f6d&rid=200.mp4","mp4_size":"156756","webp":"https:\/\/media1.giphy.com\/media\/TgV0HNvu2jHnJ0gENC\/200.webp?cid=f8e0ca6fa1cd021474189f345a08e0ded78f34ab4ca59f6d&rid=200.webp","webp_size":"306558"},"looping":{"mp4":"https:\/\/media1.giphy.com\/media\/TgV0HNvu2jHnJ0gENC\/giphy-loop.mp4?cid=f8e0ca6fa1cd021474189f345a08e0ded78f34ab4ca59f6d&rid=giphy-loop.mp4","mp4_size":"1293736"},"original_mp4":{"width":"480","height":"270","mp4":"https:\/\/media1.giphy.com\/media\/TgV0HNvu2jHnJ0gENC\/giphy.mp4?cid=f8e0ca6fa1cd021474189f345a08e0ded78f34ab4ca59f6d&rid=giphy.mp4","mp4_size":"264489"},"preview_gif":{"url":"https:\/\/media1.giphy.com\/media\/TgV0HNvu2jHnJ0gENC\/giphy-preview.gif?cid=f8e0ca6fa1cd021474189f345a08e0ded78f34ab4ca59f6d&rid=giphy-preview.gif","width":"94","height":"53","size":"48499"},"480w_still":{"url":"https:\/\/media0.giphy.com\/media\/TgV0HNvu2jHnJ0gENC\/480w_s.jpg?cid=f8e0ca6fa1cd021474189f345a08e0ded78f34ab4ca59f6d&rid=480w_s.jpg","width":"480","height":"270"}},"title":"Season 6 GIF by Bachelor in Paradise","analytics":{"onload":{"url":"https:\/\/giphy-analytics.giphy.com\/simple_analytics?response_id=a1cd021474189f345a08e0ded78f34ab4ca59f6d&event_type=GIF_TRENDING&gif_id=TgV0HNvu2jHnJ0gENC&action_type=SEEN"},"onclick":{"url":"https:\/\/giphy-analytics.giphy.com\/simple_analytics?response_id=a1cd021474189f345a08e0ded78f34ab4ca59f6d&event_type=GIF_TRENDING&gif_id=TgV0HNvu2jHnJ0gENC&action_type=CLICK"},"onsent":{"url":"https:\/\/giphy-analytics.giphy.com\/simple_analytics?response_id=a1cd021474189f345a08e0ded78f34ab4ca59f6d&event_type=GIF_TRENDING&gif_id=TgV0HNvu2jHnJ0gENC&action_type=SENT"}}}],"pagination":{"total_count":112141,"count":2,"offset":0},"meta":{"status":200,"msg":"OK","response_id":"a1cd021474189f345a08e0ded78f34ab4ca59f6d"}}